msgbuf/__init__.py
msgbuf/__main__.py
msgbuf/cli.py
msgbuf-1.0.1.dist-info/LICENSE
msgbuf-1.0.1.dist-info/METADATA
msgbuf-1.0.1.dist-info/WHEEL
msgbuf-1.0.1.dist-info/entry_points.txt
msgbuf-1.0.1.dist-info/top_level.txt
msgbuf-1.0.1.dist-info/RECORD
